pytest_common_subject/__init__.py
pytest_common_subject/exceptions.py
pytest_common_subject/fixtures.py
pytest_common_subject/mixins.py
pytest_common_subject/plugin.py
pytest_common_subject/util.py
pytest_common_subject-1.1.1.dist-info/LICENSE
pytest_common_subject-1.1.1.dist-info/METADATA
pytest_common_subject-1.1.1.dist-info/WHEEL
pytest_common_subject-1.1.1.dist-info/entry_points.txt
pytest_common_subject-1.1.1.dist-info/RECORD
