Metadata-Version: 2.1
Name: pytest-common-subject
Version: 1.1.1
Summary: pytest framework for testing different aspects of a common method
Home-page: https://github.com/theY4Kman/pytest-common-subject
License: MIT
Keywords: pytest
Author: Zach "theY4Kman" Kanzler
Author-email: they4kman@gmail.com
Requires-Python: >=3.8,<4.0
Classifier: License :: OSI Approved :: MIT License
Classifier: Programming Language :: Python :: 3
Classifier: Programming Language :: Python :: 3.8
Classifier: Programming Language :: Python :: 3.9
Classifier: Programming Language :: Python :: 3.10
Classifier: Programming Language :: Python :: 3.11
Classifier: Programming Language :: Python :: 3.12
Requires-Dist: lazy-object-proxy (>=1.3.1,<2.0.0)
Requires-Dist: pytest (>=3.6,<9)
Requires-Dist: pytest-fixture-order (>=0.1.2,<0.2.0)
Requires-Dist: pytest-lambda (>=1.3.0)
Project-URL: Repository, https://github.com/theY4Kman/pytest-common-subject
